{
    "segments": {
        "0": [
            0.0,
            5.44,
            "aggregate his and Ian Clive. Real Madrid are in countdown towards their date with"
        ],
        "1": [
            5.44,
            10.32,
            "Barcelona in 12 days time under the second classico of the season. Real now"
        ],
        "2": [
            10.32,
            15.2,
            "trail-basted by a point in the race for the title almost certainly a two-horse"
        ],
        "3": [
            15.2,
            23.68,
            "race this year and the introduction of Luka Modric after four months out will"
        ],
        "4": [
            23.68,
            28.58,
            "be part of that countdown but it's almost as if their minds are on the"
        ],
        "5": [
            28.58,
            38.14,
            "Nou Camp tonight as they haven't really managed to move through the gears in"
        ],
        "6": [
            38.14,
            43.7,
            "this game. They got away with it in the first 45 minutes big time thanks to Ronaldo."
        ],
        "7": [
            43.7,
            49.3,
            "Biggest cheer of the night as there is Modric warming up and this side I'm sure"
        ],
        "8": [
            49.3,
            52.7,
            "he'll be on pretty soon 10 to 15 minutes."
        ],
        "9": [
            52.7,
            60.34,
            "Fuchs. He's found a way through to Barnett. Casillas didn't quite gather that one in either."
        ],
        "10": [
            60.34,
            65.9,
            "Survived that spill."
        ],
        "11": [
            68.22,
            73.5,
            "It was a foul by Hervedes on Ronaldo."
        ],
        "12": [
            82.7,
            93.02,
            "He just stood on his foot didn't he there. Hervedes is just about to leap."
        ],
        "13": [
            97.74,
            100.94,
            "Fabio Quintral."
        ],
        "14": [
            101.78,
            106.26,
            "Real Madrid do have a clear week ahead of that game at the Nou Camp on Saturday"
        ],
        "15": [
            106.26,
            111.66,
            "week. Barcelona face Manchester City four days before it."
        ],
        "16": [
            112.7,
            118.94,
            "Sané."
        ],
        "17": [
            118.94,
            124.3,
            "Neustadt. Maier who's been lively and creative."
        ],
        "18": [
            124.3,
            126.34,
            "Barnett."
        ],
        "19": [
            126.34,
            130.78,
            "Swatted a little too long on the board and Kadira got to him."
        ],
        "20": [
            130.78,
            134.98,
            "They've put two or three of those little passes together in the middle of the park."
        ],
        "21": [
            134.98,
            138.66,
            "They've always had their wing-backs in good positions. Barnett down the right."
        ],
        "22": [
            138.66,
            142.1,
            "Fuchs down the left there."
        ],
        "23": [
            142.7,
            157.9,
            "Two of the back three forward to join Boutella who's right on the line alongside Casillas."
        ],
        "24": [
            157.9,
            164.06,
            "Cut out by Benzema helping out. Here's Bale."
        ],
        "25": [
            164.06,
            168.26,
            "Caught in possession by Hervedes. No free kick."
        ],
        "26": [
            169.06,
            171.46,
            "What's up with Gareth Bale Andy?"
        ],
        "27": [
            171.46,
            177.06,
            "He's just lacking confidence Clive. He's having that little spell where every decision you make is the wrong one."
        ],
        "28": [
            177.06,
            180.26,
            "You knock a ball in early you should have had an extra touch and vice versa."
        ],
        "29": [
            180.26,
            185.14,
            "It's just not happening for him and he's got to keep going and get through it."
        ],
        "30": [
            185.14,
            188.18,
            "Isco has fouled Ronaldo at the same time of asking."
        ],
        "31": [
            188.18,
            194.26,
            "And here's Isco. He lost his footing as he went for goal."
        ],
        "32": [
            194.26,
            198.26,
            "His deflections are a corner kick."
        ],
        "33": [
            198.26,
            220.26,
            "Cross with the corner. That's really well held by Timo Gjallarhoyt."
        ],
        "34": [
            220.26,
            224.26,
            "He's got a free kick for his troubles too."
        ],
        "35": [
            225.26,
            228.26,
            "Confident in coming and grabbing it isn't he the goalkeeper."
        ],
        "36": [
            228.26,
            231.26,
            "He's not standing there waiting for people to deal with it."
        ],
        "37": [
            231.26,
            233.26,
            "It's always good to see that."
        ],
        "38": [
            233.26,
            236.26,
            "Just comes out of his hands at the last moment there."
        ],
        "39": [
            236.26,
            239.26,
            "He was a little bit fortunate maybe to get a free kick there."
        ],
        "40": [
            239.26,
            242.26,
            "He's not that much contact."
        ],
        "41": [
            242.26,
            248.26,
            "I think it's his collision with the planet rather than with Benzema who shook it out of his hands."
        ],
        "42": [
            248.26,
            252.26,
            "It's the Japanese World Cup right back at Sudo Ishida."
        ],
        "43": [
            252.26,
            254.26,
            "And Schalke."
        ],
        "44": [
            258.26,
            264.26,
            "Without half a dozen first team players one reason or another."
        ],
        "45": [
            264.26,
            267.26,
            "So not too much choice for Roberto Di Matteo on the bench but they have."
        ],
        "46": [
            267.26,
            269.26,
            "Another corner here."
        ],
        "47": [
            278.26,
            292.26,
            "It's easy enough for Schalke to find Fuchs there."
        ],
        "48": [
            292.26,
            296.26,
            "Barnett is onside. It's away by Ronaldo."
        ],
        "49": [
            296.26,
            299.26,
            "Now can Isco and Benzema conjure a counter attack."
        ],
        "50": [
            299.26,
            301.26,
            "There's your answer."
        ],
        "51": [
            301.26,
            304.26,
            "Clumsy from Benzema. Poor ball."
        ],
        "52": [
            305.26,
            307.26,
            "Timing of the pass as well."
        ],
        "53": [
            307.26,
            310.26,
            "Unnecessary. Isco's done well to pinch it back."
        ],
        "54": [
            310.26,
            313.26,
            "Still as well as anybody for Real Madrid."
        ],
        "55": [
            313.26,
            316.26,
            "Benzema's played it behind Bale."
        ],
        "56": [
            316.26,
            318.26,
            "They're not connecting those three."
        ],
        "57": [
            325.26,
            329.26,
            "It's amazing to think where they were through September, October, November."
        ],
        "58": [
            329.26,
            333.26,
            "22 consecutive wins."
        ],
        "59": [
            333.26,
            335.26,
            "Incredible run they were having at that point."
        ],
        "60": [
            335.26,
            338.26,
            "Everything was flowing so naturally, so freely."
        ],
        "61": [
            338.26,
            340.26,
            "It's amazing how quick it turns."
        ],
        "62": [
            340.26,
            342.26,
            "And when it disappears, when that confidence goes,"
        ],
        "63": [
            342.26,
            345.26,
            "that rhythm that you've got just seems to disappear."
        ],
        "64": [
            345.26,
            347.26,
            "It's very, very tough to get it back."
        ],
        "65": [
            347.26,
            349.26,
            "It's that winter break that interrupted them."
        ],
        "66": [
            349.26,
            351.26,
            "It's overrated winter break."
        ],
        "67": [
            363.26,
            365.26,
            "It's a clear push by Leicester. Short of Bale."
        ],
        "68": [
            394.26,
            396.26,
            "Samp are interested in signing him permanently."
        ],
        "69": [
            407.26,
            408.26,
            "Quintra."
        ],
        "70": [
            410.26,
            411.26,
            "Benzema."
        ],
        "71": [
            413.26,
            415.26,
            "There's Fabio Quintra."
        ],
        "72": [
            415.26,
            417.26,
            "It's run for Benzema, a run kindly."
        ],
        "73": [
            417.26,
            419.26,
            "And Karim Benzema, surely!"
        ],
        "74": [
            420.26,
            423.26,
            "Real Madrid take the lead for the first time on the night."
        ],
        "75": [
            425.26,
            428.26,
            "Karim Benzema has got the goal."
        ],
        "76": [
            428.26,
            432.26,
            "20 for the season, for the fifth season in a row for him."
        ],
        "77": [
            433.26,
            438.26,
            "And maybe that will unlock the gates."
        ],
        "78": [
            440.26,
            443.26,
            "Real Madrid have a clear three-goal aggregate lead."
        ],
        "79": [
            443.26,
            445.26,
            "He started it, Benzema, then he's just there."
        ],
        "80": [
            445.26,
            446.26,
            "Close to being offside."
        ],
        "81": [
            446.26,
            447.26,
            "Very."
        ],
        "82": [
            447.26,
            449.26,
            "Just gets the benefit of the doubt."
        ],
        "83": [
            449.26,
            450.26,
            "One or two little ricochets."
        ],
        "84": [
            450.26,
            451.26,
            "Full carny for him."
        ],
        "85": [
            451.26,
            454.26,
            "But then he's got the composure to have that extra touch there."
        ],
        "86": [
            454.26,
            456.26,
            "And again there."
        ],
        "87": [
            456.26,
            460.26,
            "To just bring the goalkeeper under the ball."
        ],
        "88": [
            460.26,
            464.26,
            "Eventually just leaves himself with an empty net just to pop it in."
        ],
        "89": [
            464.26,
            467.26,
            "A little bit of good fortune, but good persistence from Benzema."
        ],
        "90": [
            467.26,
            469.26,
            "He's not had the greatest night."
        ],
        "91": [
            469.26,
            470.26,
            "Not been easy for him up there."
        ],
        "92": [
            470.26,
            472.26,
            "Gets himself a goal."
        ],
        "93": [
            473.26,
            478.26,
            "That's half a dozen of his 20 goals for the season in this competition."
        ],
        "94": [
            478.26,
            482.26,
            "Karim Benzema has a fantastic goal-scoring record in the Champions League."
        ],
        "95": [
            482.26,
            485.26,
            "42 in 61 games."
        ],
        "96": [
            485.26,
            492.26,
            "And he's actually knocking on the door of the top 10 of the all-time Champions League goal-scorers now."
        ],
        "97": [
            492.26,
            494.26,
            "One step rather slid in there."
        ],
        "98": [
            494.26,
            496.26,
            "Wasn't a lot of control about the challenge."
        ],
        "99": [
            496.26,
            498.26,
            "Again it's because he's got his foot up a bit."
        ],
        "100": [
            498.26,
            504.26,
            "I think Clive is the reason why the referee maybe wants to have a little word."
        ],
        "101": [
            512.26,
            515.26,
            "He's always getting there first in the challenge, wasn't he?"
        ],
        "102": [
            515.26,
            517.26,
            "It's just, again, momentum."
        ],
        "103": [
            517.26,
            519.26,
            "All you can do about it is just get in there."
        ],
        "104": [
            520.26,
            521.26,
            "Again, momentum."
        ],
        "105": [
            521.26,
            523.26,
            "All you can do about that when you commit to a challenge."
        ],
        "106": [
            525.26,
            527.26,
            "Schalke need three goals now, so..."
        ],
        "107": [
            529.26,
            531.26,
            "A little bit of the realism has returned to the tie."
        ],
        "108": [
            533.26,
            535.26,
            "And Real Madrid relax."
        ],
        "109": [
            537.26,
            538.26,
            "Start to enjoy the night."
        ],
        "110": [
            541.26,
            543.26,
            "Mike Coentrao is holding there."
        ],
        "111": [
            543.26,
            546.26,
            "That might just be a bit too far for him."
        ],
        "112": [
            550.26,
            552.26,
            "He's been the British player this season."
        ],
        "113": [
            553.26,
            556.26,
            "It's only his ninth start of the season."
        ],
        "114": [
            563.26,
            567.26,
            "Of course you can hear because Luka Modric has completed his warm-up and is ready to return."
        ],
        "115": [
            580.26,
            582.26,
            "Sané."
        ],
        "116": [
            588.26,
            590.26,
            "Slesic to Matic."
        ],
        "117": [
            592.26,
            594.26,
            "The other game in the last 16 this evening."
        ],
        "118": [
            594.26,
            596.26,
            "Porto now have a clear lead."
        ],
        "119": [
            596.26,
            599.26,
            "2-0 they lead on the night against Barcelona."
        ],
        "120": [
            599.26,
            602.26,
            "And in the drug out, 3-1 on aggregate."
        ],
        "121": [
            602.26,
            606.26,
            "We'll get to see highlights of that game on ITV at 10.40 this evening."
        ],
        "122": [
            607.26,
            609.26,
            "Along with the reaction from here."
        ],
        "123": [
            610.26,
            612.26,
            "It's been a pretty extraordinary night so far in the Bernabeu."
        ],
        "124": [
            613.26,
            614.26,
            "10.40 ITV."
        ],
        "125": [
            619.26,
            620.26,
            "Barnetta."
        ],
        "126": [
            621.26,
            622.26,
            "Got away from Coentrao."
        ],
        "127": [
            623.26,
            626.26,
            "Huntelaar has always just lacked that extra yard of pace."
        ],
        "128": [
            627.26,
            630.26,
            "Pepe's quick. He's good like that."
        ],
        "129": [
            630.26,
            632.26,
            "Barnetta did really well with the pass to Huntelaar."
        ],
        "130": [
            632.26,
            634.26,
            "It was a poor one. He always favoured the centre half."
        ],
        "131": [
            637.26,
            639.26,
            "It's been a crazy evening."
        ],
        "132": [
            639.26,
            642.26,
            "Just concentrate on your delivery here."
        ],
        "133": [
            642.26,
            643.26,
            "Put it into a good area."
        ],
        "134": [
            644.26,
            646.26,
            "Put a pass up and score it again."
        ],
        "135": [
            651.26,
            652.26,
            "Fuchs with the corner."
        ],
        "136": [
            653.26,
            654.26,
            "Casillas rather pored at it."
        ],
        "137": [
            655.26,
            656.26,
            "This is Matic."
        ],
        "138": [
            667.26,
            669.26,
            "It's a terrific ball from Neustadt."
        ],
        "139": [
            670.26,
            671.26,
            "Fuchs has found Sané."
        ],
        "140": [
            672.26,
            674.26,
            "Sané's just invited to shoot and score."
        ],
        "141": [
            675.26,
            676.26,
            "It's 3-3."
        ],
        "142": [
            679.26,
            681.26,
            "What a moment for Leroy Sané."
        ],
        "143": [
            682.26,
            684.26,
            "His European debut in the Bernabeu."
        ],
        "144": [
            685.26,
            689.26,
            "And the 19-year-old has just fired Roberto Di Matteo's team back on terms."
        ],
        "145": [
            690.26,
            691.26,
            "They need two more."
        ],
        "146": [
            691.26,
            692.26,
            "Really good football though."
        ],
        "147": [
            692.26,
            693.26,
            "The way they kept the ball."
        ],
        "148": [
            693.26,
            696.26,
            "It went out to Christian Fuchs who ended up just dropping it into Sané."
        ],
        "149": [
            696.26,
            697.26,
            "Great finish."
        ],
        "150": [
            698.26,
            699.26,
            "Really, really good finish."
        ],
        "151": [
            699.26,
            700.26,
            "That's a clever little ball."
        ],
        "152": [
            700.26,
            701.26,
            "Here, it takes a bit of time."
        ],
        "153": [
            701.26,
            703.26,
            "He knows exactly what he wants to do."
        ],
        "154": [
            703.26,
            704.26,
            "Goalkeeper again."
        ],
        "155": [
            704.26,
            706.26,
            "Any danger of him getting near something this evening?"
        ],
        "156": [
            706.26,
            707.26,
            "I'm not sure."
        ],
        "157": [
            708.26,
            710.26,
            "That's a good goal. Great goal."
        ],
        "158": [
            710.26,
            711.26,
            "Goal."
        ],
        "159": [
            717.26,
            722.26,
            "Herger has been replaced by a really outstanding young prospect by the name of Leon Goretzka."
        ],
        "160": [
            723.26,
            724.26,
            "Number eight, he's 20 years of age."
        ],
        "161": [
            725.26,
            728.26,
            "Came back on Saturday after eight months out of injury."
        ],
        "162": [
            732.26,
            735.26,
            "There are high hopes for Goretzka in German football."
        ],
        "163": [
            737.26,
            738.26,
            "German leads the field."
        ],
        "164": [
            738.26,
            739.26,
            "He's a good ear up."
        ],
        "165": [
            739.26,
            740.26,
            "And just listen."
        ],
        "166": [
            742.26,
            744.26,
            "To the welcome back for Luka Modric."
        ],
        "167": [
            745.26,
            749.26,
            "One of two changes because Fabio Quintral is making way for Marcelo."
        ],
        "168": [
            752.26,
            760.26,
            "But the attention all on Modric who on November the 16th suffered a thigh injury on international duty."
        ],
        "169": [
            761.26,
            764.26,
            "He's undergone stem cell treatment in the Basque country."
        ],
        "170": [
            764.26,
            767.26,
            "He's seen a specialist in Munich, a physio in Antwerp."
        ],
        "171": [
            769.26,
            775.26,
            "In a bid to get him ready to play a big part in Real Madrid's climax of the season."
        ],
        "172": [
            775.26,
            780.26,
            "Here is La Liga's outstanding midfield player last season, Luka Modric."
        ],
        "173": [
            789.26,
            790.26,
            "Now Fuchs."
        ],
        "174": [
            792.26,
            794.26,
            "Time for Marcelo."
        ],
        "175": [
            794.26,
            796.26,
            "He has been the regular left back this season."
        ],
        "176": [
            796.26,
            799.26,
            "He's actually a yellow card away from a Champions League suspension."
        ],
        "177": [
            799.26,
            802.26,
            "Which is why I think he was left out of the starting line up tonight."
        ],
        "178": [
            802.26,
            804.26,
            "But now Quintral has a yellow card."
        ],
        "179": [
            804.26,
            806.26,
            "So Marcelo here has come on."
        ],
        "180": [
            807.26,
            809.26,
            "Back in the Brazilian squad this week."
        ],
        "181": [
            811.26,
            812.26,
            "Close to Modric."
        ],
        "182": [
            814.26,
            816.26,
            "Modric already knitting things together."
        ],
        "183": [
            825.26,
            828.26,
            "Ronaldo, Modric, Isco."
        ],
        "184": [
            831.26,
            832.26,
            "Marcelo."
        ],
        "185": [
            834.26,
            835.26,
            "Nestor crosses."
        ],
        "186": [
            841.26,
            842.26,
            "Throw in."
        ],
        "187": [
            844.26,
            846.26,
            "Javier Hernandez all ready."
        ],
        "188": [
            849.26,
            851.26,
            "This is that clever little ball from Christian Fuchs."
        ],
        "189": [
            851.26,
            853.26,
            "Sane has got a lot of room. Nobody really getting close."
        ],
        "190": [
            853.26,
            855.26,
            "Nobody wanting to stop the shot, deny him."
        ],
        "191": [
            855.26,
            857.26,
            "He's got plenty of time to have a touch, lift his head."
        ],
        "192": [
            858.26,
            861.26,
            "Just stroke that beautiful pass. Casillas."
        ],
        "193": [
            881.26,
            882.26,
            "Bale."
        ],
        "194": [
            888.26,
            889.26,
            "Bale."
        ],
        "195": [
            890.26,
            891.26,
            "Marmelado."
        ],
        "196": [
            892.26,
            893.26,
            "It's too far in front of Bale."
        ],
        "197": [
            894.26,
            896.26,
            "Stasic away but only as far as Modric."
        ],
        "198": [
            902.26,
            903.26,
            "Isco."
        ],
        "199": [
            904.26,
            905.26,
            "Benzema."
        ],
        "200": [
            907.26,
            909.26,
            "Isco trying to get on the dangerous side of Hernandez."
        ],
        "201": [
            909.26,
            911.26,
            "It's good defending by the Schalke skipper."
        ],
        "202": [
            911.26,
            912.26,
            "Really good challenge that from Hernandez."
        ],
        "203": [
            912.26,
            914.26,
            "Clever ball that from Benzema."
        ],
        "204": [
            914.26,
            915.26,
            "Here's Goretzka."
        ],
        "205": [
            924.26,
            925.26,
            "There's Stasic."
        ],
        "206": [
            930.26,
            933.26,
            "Schalke have been in this game from the outset."
        ],
        "207": [
            934.26,
            935.26,
            "Twice they've led."
        ],
        "208": [
            936.26,
            938.26,
            "Goretzka finding Fuchs."
        ],
        "209": [
            951.26,
            954.26,
            "It's a way to hold the 2-0 10-0 in the Premier League."
        ],
        "210": [
            954.26,
            957.26,
            "Benedict Hernandez by saying publicly in the last couple of weeks"
        ],
        "211": [
            957.26,
            959.26,
            "that he wants to play in England."
        ],
        "212": [
            959.26,
            961.26,
            "He's got a couple of years left on his contract."
        ],
        "213": [
            961.26,
            963.26,
            "He was only 27 last month."
        ],
        "214": [
            963.26,
            964.26,
            "A German World Cup winner."
        ],
        "215": [
            964.26,
            966.26,
            "Number 4, Benedikt Hernandez."
        ],
        "216": [
            967.26,
            970.26,
            "I'll have 15% of the deal if anybody makes it in."
        ],
        "217": [
            970.26,
            971.26,
            "I'll try it for you, mate."
        ],
        "218": [
            980.26,
            981.26,
            "Barnett in the corner."
        ],
        "219": [
            986.26,
            987.26,
            "It's Hernandez with the header."
        ],
        "220": [
            987.26,
            990.26,
            "Misheader. He's found a way back to Barnett somehow."
        ],
        "221": [
            990.26,
            991.26,
            "Oh!"
        ],
        "222": [
            992.26,
            994.26,
            "Casillas trying to save that."
        ],
        "223": [
            994.26,
            995.26,
            "It whizzed past him."
        ],
        "224": [
            996.26,
            997.26,
            "Gone for a throw-in."
        ],
        "225": [
            997.26,
            999.26,
            "Throw-in to Schalke."
        ],
        "226": [
            999.26,
            1002.26,
            "So maybe Casillas got something on there."
        ],
        "227": [
            1004.26,
            1005.26,
            "The corner initially was a poor one."
        ],
        "228": [
            1005.26,
            1008.26,
            "Hernandez as well just trying to get that one on target."
        ],
        "229": [
            1008.26,
            1012.26,
            "It hits Luka Modric actually on the knee and just ends up beating the goalkeeper."
        ],
        "230": [
            1012.26,
            1014.26,
            "Wow. Very, very close."
        ],
        "231": [
            1021.26,
            1022.26,
            "Sane."
        ],
        "232": [
            1023.26,
            1024.26,
            "Bayern."
        ],
        "233": [
            1029.26,
            1030.26,
            "Barnett has crossed."
        ],
        "234": [
            1030.26,
            1032.26,
            "It's towards Wuntelar."
        ],
        "235": [
            1032.26,
            1034.26,
            "Mbappé got there in the nick of time."
        ],
        "236": [
            1034.26,
            1035.26,
            "Away by Pepe."
        ],
        "237": [
            1039.26,
            1041.26,
            "A rather timid touch from Bale."
        ],
        "238": [
            1051.26,
            1052.26,
            "What a save."
        ],
        "239": [
            1065.26,
            1066.26,
            "Quite right they're keeping the ball."
        ],
        "240": [
            1066.26,
            1070.26,
            "There's plenty of time left in this game if they were to get the next goal."
        ],
        "241": [
            1072.26,
            1074.26,
            "Oh, and a full bit of the ball still mid-finish."
        ],
        "242": [
            1074.26,
            1077.26,
            "The song you can hear a bit from the Schalke contingent."
        ],
        "243": [
            1078.26,
            1080.26,
            "Benzema towards Isco."
        ],
        "244": [
            1081.26,
            1082.26,
            "Ronaldo."
        ],
        "245": [
            1082.26,
            1083.26,
            "Found space."
        ],
        "246": [
            1085.26,
            1086.26,
            "He can quite get hold of it."
        ],
        "247": [
            1088.26,
            1094.26,
            "Every time he turns and lines up the shot, you just expect it to find a corner of the net."
        ],
        "248": [
            1094.26,
            1096.26,
            "Just doesn't quite catch that one."
        ],
        "249": [
            1097.26,
            1099.26,
            "Goretzka to Maia."
        ],
        "250": [
            1099.26,
            1101.26,
            "That's the position he likes to get in. He's done it very well again."
        ],
        "251": [
            1102.26,
            1103.26,
            "Sane."
        ],
        "252": [
            1105.26,
            1106.26,
            "Back to Max Maia."
        ],
        "253": [
            1109.26,
            1111.26,
            "Unlucky. Good run. Good combination play."
        ],
        "254": [
            1111.26,
            1112.26,
            "Sane and Maia."
        ],
        "255": [
            1116.26,
            1118.26,
            "It's his fourth job in management already."
        ],
        "256": [
            1118.26,
            1119.26,
            "He's got a good team."
        ],
        "257": [
            1119.26,
            1120.26,
            "He's got a good team."
        ],
        "258": [
            1120.26,
            1121.26,
            "He's got a good team."
        ],
        "259": [
            1121.26,
            1122.26,
            "He's got a good team."
        ],
        "260": [
            1122.26,
            1123.26,
            "He's got a good team."
        ],
        "261": [
            1123.26,
            1124.26,
            "He's got a good team."
        ],
        "262": [
            1124.26,
            1125.26,
            "He's got a good team."
        ],
        "263": [
            1125.26,
            1126.26,
            "Fourth job in management."
        ],
        "264": [
            1126.26,
            1127.26,
            "Roberto Di Matteo."
        ],
        "265": [
            1127.26,
            1128.26,
            "Maybe the defining one."
        ],
        "266": [
            1129.26,
            1131.26,
            "Less than nine months in charge with Chelsea."
        ],
        "267": [
            1131.26,
            1134.26,
            "Won the FA Cup as well as Champions League, remember?"
        ],
        "268": [
            1134.26,
            1138.26,
            "But he was a caretaker manager who was replaced by another in the end, Rafa Benitez."
        ],
        "269": [
            1140.26,
            1144.26,
            "He's done a lot of work for nearly two years before Schalke came calling."
        ],
        "270": [
            1144.26,
            1154.26,
            "Porto well on their way to the quarterfinals."
        ],
        "271": [
            1154.26,
            1159.26,
            "They now lead by three goals to nil against Basel of my 41."
        ],
        "272": [
            1159.26,
            1162.26,
            "It's Real Madrid player Casemiro who's on loan to the Mooscot club."
        ],
        "273": [
            1163.26,
            1164.26,
            "Here's a chance for Abelard."
        ],
        "274": [
            1165.26,
            1166.26,
            "He's got five."
        ],
        "275": [
            1166.26,
            1167.26,
            "Another Reuter."
        ],
        "276": [
            1169.26,
            1170.26,
            "Good save."
        ],
        "277": [
            1170.26,
            1171.26,
            "Really good stop there."
        ],
        "278": [
            1171.26,
            1172.26,
            "Big chance."
        ],
        "279": [
            1175.26,
            1181.26,
            "Not as surprised as I was that he found himself in that position."
        ],
        "280": [
            1195.26,
            1198.26,
            "Madrid aren't quite in the quarterfinals yet."
        ],
        "281": [
            1199.26,
            1202.26,
            "Twice they trailed here this evening."
        ],
        "282": [
            1202.26,
            1207.26,
            "Two heady goals from Cristiano Ronaldo have been the equalisers."
        ],
        "283": [
            1208.26,
            1212.26,
            "Benzema gave them the lead for the first time on the night."
        ],
        "284": [
            1212.26,
            1217.26,
            "But within four minutes of that goal, Leroy Sané will draw on Schalke level."
        ],
        "285": [
            1217.26,
            1218.26,
            "Good run from Gareth Bale."
        ],
        "286": [
            1218.26,
            1219.26,
            "Great ball as well."
        ],
        "287": [
            1220.26,
            1223.26,
            "Couldn't be anybody else on the field that would have knocked that one in."
        ],
        "288": [
            1224.26,
            1228.26,
            "Here is Alvaro Abelard back on his normal post."
        ],
        "289": [
            1230.26,
            1231.26,
            "Modric."
        ],
        "290": [
            1233.26,
            1234.26,
            "Marcelo."
        ],
        "291": [
            1238.26,
            1239.26,
            "Benzema."
        ],
        "292": [
            1239.26,
            1240.26,
            "Pente finding Ronaldo."
        ],
        "293": [
            1269.26,
            1281.26,
            "Modric finding Isco."
        ],
        "294": [
            1281.26,
            1282.26,
            "Now Marcelo."
        ],
        "295": [
            1287.26,
            1289.26,
            "He's found a way through to Benzema."
        ],
        "296": [
            1291.26,
            1292.26,
            "Here comes Abelard."
        ],
        "297": [
            1295.26,
            1296.26,
            "Isco."
        ],
        "298": [
            1296.26,
            1297.26,
            "Terrific control."
        ],
        "299": [
            1298.26,
            1299.26,
            "Put out by Hervedes."
        ],
        "300": [
            1306.26,
            1307.26,
            "Good poise from Gareth."
        ],
        "301": [
            1312.26,
            1313.26,
            "Not that well."
        ],
        "302": [
            1313.26,
            1314.26,
            "Neustadt to Hervedes."
        ],
        "303": [
            1318.26,
            1319.26,
            "Swept out into the path."
        ],
        "304": [
            1320.26,
            1321.26,
            "Christian Fuchs."
        ],
        "305": [
            1323.26,
            1324.26,
            "Neustadt."
        ],
        "306": [
            1327.26,
            1330.26,
            "Just think Christian Fuchs has the wrong option."
        ],
        "307": [
            1330.26,
            1332.26,
            "They switched the play well to him there."
        ],
        "308": [
            1332.26,
            1334.26,
            "Two blue shirts in the box."
        ],
        "309": [
            1334.26,
            1336.26,
            "This was a few seconds earlier."
        ],
        "310": [
            1336.26,
            1337.26,
            "Good touch from Isco."
        ],
        "311": [
            1337.26,
            1339.26,
            "Hervedes read it very well."
        ],
        "312": [
            1341.26,
            1342.26,
            "Good skill."
        ],
        "313": [
            1358.26,
            1364.26,
            "He was complaining over the weekend that he's not allowed to fail even with a single pass."
        ],
        "314": [
            1364.26,
            1365.26,
            "A bit sorry for himself."
        ],
        "315": [
            1365.26,
            1370.26,
            "Karim Benzema after being substituted in the defeat in Bilbao."
        ],
        "316": [
            1371.26,
            1375.26,
            "Probably a language of one or two of them hasn't been all that good this evening."
        ],
        "317": [
            1378.26,
            1380.26,
            "A little world weary Real Madrid."
        ],
        "318": [
            1381.26,
            1387.26,
            "Schalke themselves looking just a little bit leggy the last few minutes."
        ],
        "319": [
            1387.26,
            1389.26,
            "Matavie is had to make changes already."
        ],
        "320": [
            1391.26,
            1397.26,
            "Just whether they have got enough spring in their step to really pose a serious threat to the game tonight."
        ],
        "321": [
            1400.26,
            1401.26,
            "Will Scipi be back."
        ],
        "322": [
            1401.26,
            1403.26,
            "Or when take a look among the other teams."
        ],
        "323": [
            1403.26,
            1409.98,
            "already. I just wonder if they've got enough spring in their step to really pose a serious"
        ],
        "324": [
            1409.98,
            1412.18,
            "threat the remainder of this game. Still plenty of time."
        ],
        "325": [
            1412.18,
            1416.18,
            "As you say, I think they'll need the next goal. They need two to get back into the tie."
        ],
        "326": [
            1418.18,
            1421.18,
            "Red plate. No dispossessed."
        ],
        "327": [
            1424.18,
            1428.18,
            "Shunshin Ban, rather mournfully, not very quickly either."
        ],
        "328": [
            1429.1,
            1431.1,
            "Fuchs, Sané,"
        ],
        "329": [
            1432.1,
            1434.1,
            "Maier,"
        ],
        "330": [
            1437.1,
            1439.1,
            "Barnetta,"
        ],
        "331": [
            1439.1,
            1441.1,
            "Untala,"
        ],
        "332": [
            1441.1,
            1443.1,
            "quite come off for him."
        ],
        "333": [
            1445.1,
            1446.1,
            "Isco can break."
        ],
        "334": [
            1446.1,
            1449.1,
            "Ronaldo to his left, Benzema ahead of him."
        ],
        "335": [
            1451.1,
            1454.1,
            "Bayern and Kroos are arriving too. Cristiano Ronaldo,"
        ],
        "336": [
            1455.1,
            1456.1,
            "Isco,"
        ],
        "337": [
            1456.1,
            1458.1,
            "here is Tony Kroos!"
        ],
        "338": [
            1459.1,
            1462.18,
            "Good save by Vallen-Roy, Turin came to him at a good height."
        ],
        "339": [
            1462.18,
            1464.18,
            "It was pretty straightforward in the end."
        ],
        "340": [
            1465.18,
            1466.18,
            "Decent play there."
        ],
        "341": [
            1466.18,
            1469.18,
            "The man over there, good reverse pass from Isco."
        ],
        "342": [
            1469.18,
            1471.18,
            "Straight out the goalkeeper here."
        ],
        "343": [
            1471.18,
            1473.18,
            "Expecting to make that with the sort of saves."
        ],
        "344": [
            1474.18,
            1476.18,
            "Expect actually Tony Kroos to get more goals,"
        ],
        "345": [
            1476.18,
            1477.18,
            "driving this Real Madrid team."
        ],
        "346": [
            1477.18,
            1478.18,
            "What? This season?"
        ],
        "347": [
            1478.18,
            1479.18,
            "Yeah."
        ],
        "348": [
            1480.18,
            1481.18,
            "A player of his quality."
        ],
        "349": [
            1482.18,
            1484.18,
            "Obviously when he's playing deeper without Modric,"
        ],
        "350": [
            1484.18,
            1487.18,
            "he's probably felt like he's the one to get everything going for them."
        ],
        "351": [
            1488.18,
            1490.18,
            "Kroos with the corner, Bale with the header."
        ],
        "352": [
            1500.18,
            1502.18,
            "He's got a reputation"
        ],
        "353": [
            1502.18,
            1505.18,
            "for being a good superstar manager."
        ],
        "354": [
            1505.18,
            1507.18,
            "Criticised recently for lacking a firm hand,"
        ],
        "355": [
            1508.18,
            1510.18,
            "as Carlo Ancelotti has pointed out,"
        ],
        "356": [
            1510.18,
            1512.18,
            "it's his more gentle approach that's"
        ],
        "357": [
            1512.18,
            1514.18,
            "won this competition at two different clubs now."
        ],
        "358": [
            1514.18,
            1518.18,
            "It's not his style to trumpet his personal achievements,"
        ],
        "359": [
            1518.18,
            1521.18,
            "but he's having to defend his record at the moment."
        ],
        "360": [
            1524.18,
            1527.18,
            "I think he trusts his key players, his senior players, doesn't he?"
        ],
        "361": [
            1527.18,
            1529.18,
            "That's what Carlo Ancelotti does."
        ],
        "362": [
            1529.18,
            1532.18,
            "He does that well, and I respect that."
        ],
        "363": [
            1532.18,
            1535.18,
            "When he realises, recognises when they're not quite at it,"
        ],
        "364": [
            1535.18,
            1537.18,
            "he's got to stand by and give them support."
        ],
        "365": [
            1537.18,
            1539.18,
            "He's lost it. Here's Maia."
        ],
        "366": [
            1543.18,
            1544.18,
            "Noise detector."
        ],
        "367": [
            1544.18,
            1546.18,
            "That was ambitious."
        ],
        "368": [
            1548.18,
            1549.18,
            "Sorry."
        ],
        "369": [
            1569.18,
            1571.18,
            "The scoreline remains the same. That's a big if."
        ],
        "370": [
            1571.18,
            1574.18,
            "It's a rather mixed blessing that he passes to the quarter-finals."
        ],
        "371": [
            1574.18,
            1578.18,
            "I don't think there'll be too many glorious headlines"
        ],
        "372": [
            1578.18,
            1581.18,
            "awaiting Real Madrid in the morning."
        ],
        "373": [
            1584.18,
            1585.18,
            "It's good for Modric."
        ],
        "374": [
            1585.18,
            1586.18,
            "Good."
        ],
        "375": [
            1586.18,
            1587.18,
            "Lifted into the path of Bale."
        ],
        "376": [
            1587.18,
            1589.18,
            "This is him at his best."
        ],
        "377": [
            1592.18,
            1594.18,
            "It wasn't a cross hit with any real conviction."
        ],
        "378": [
            1594.18,
            1596.18,
            "Herbert is away."
        ],
        "379": [
            1597.18,
            1598.18,
            "Barnetta."
        ],
        "380": [
            1599.18,
            1601.18,
            "He's found a way out to Maia."
        ],
        "381": [
            1603.18,
            1605.18,
            "Now, Buntelar."
        ],
        "382": [
            1610.18,
            1611.18,
            "Maia."
        ],
        "383": [
            1613.18,
            1615.18,
            "Fuchs with a chance to cross."
        ],
        "384": [
            1617.18,
            1618.18,
            "And it's by Varane."
        ],
        "385": [
            1621.18,
            1623.18,
            "Herbert is strong in the back."
        ],
        "386": [
            1624.18,
            1626.18,
            "Herbert is strong in the challenge."
        ],
        "387": [
            1626.18,
            1629.18,
            "Benzema resisted, though, and Kroos finds Marsella."
        ],
        "388": [
            1630.18,
            1632.18,
            "Benzema back on the ball."
        ],
        "389": [
            1633.18,
            1634.18,
            "Ronaldo."
        ],
        "390": [
            1641.18,
            1643.18,
            "Couldn't quite lift the cross in the way that he wanted."
        ],
        "391": [
            1643.18,
            1644.18,
            "Barnetta cleared."
        ],
        "392": [
            1653.18,
            1654.18,
            "Bale."
        ],
        "393": [
            1674.18,
            1675.18,
            "Bale."
        ],
        "394": [
            1677.18,
            1678.18,
            "That's more like it."
        ],
        "395": [
            1678.18,
            1680.18,
            "Stung the fingertips of Mellon Reuter."
        ],
        "396": [
            1680.18,
            1682.18,
            "Yeah, it was a good hit, that, from Gareth Bale."
        ],
        "397": [
            1682.18,
            1685.18,
            "As soon as he picked that up, a little bit more positive in his mind"
        ],
        "398": [
            1685.18,
            1687.18,
            "to drive into the space in front of him"
        ],
        "399": [
            1688.18,
            1691.18,
            "and hit it, rather than always looking for somebody else."
        ],
        "400": [
            1694.18,
            1697.18,
            "Marsella taking a ring road run."
        ],
        "401": [
            1697.18,
            1698.18,
            "Barnetta."
        ],
        "402": [
            1699.18,
            1701.18,
            "Will he be able to deal with a cross?"
        ],
        "403": [
            1712.18,
            1713.18,
            "Go on, go on."
        ],
        "404": [
            1728.18,
            1731.18,
            "Ball's for Isco, he's a real crowd favourite."
        ],
        "405": [
            1731.18,
            1734.18,
            "He has put in a shift in every game he's played this season."
        ],
        "406": [
            1734.18,
            1736.18,
            "He has played just about every game."
        ],
        "407": [
            1742.18,
            1743.18,
            "I hope it is."
        ],
        "408": [
            1743.18,
            1745.18,
            "Seeking out Fuchs on a run-off, a lower,"
        ],
        "409": [
            1745.18,
            1748.18,
            "and you can see he's seen to be on collision course there."
        ],
        "410": [
            1749.18,
            1750.18,
            "Captain in charge."
        ],
        "411": [
            1753.18,
            1754.18,
            "Bale."
        ],
        "412": [
            1755.18,
            1756.18,
            "Ronaldo."
        ],
        "413": [
            1762.18,
            1764.18,
            "That's a terrific pass, Kroos."
        ],
        "414": [
            1765.18,
            1766.18,
            "Now Isco."
        ],
        "415": [
            1767.18,
            1768.18,
            "And he's got it."
        ],
        "416": [
            1768.18,
            1769.18,
            "That's a terrific pass, Kroos."
        ],
        "417": [
            1770.18,
            1771.18,
            "Now Isco."
        ],
        "418": [
            1772.18,
            1773.18,
            "Marsella."
        ],
        "419": [
            1774.18,
            1776.18,
            "Pull back to Benzema."
        ],
        "420": [
            1776.18,
            1777.18,
            "Tees up Isco."
        ],
        "421": [
            1787.18,
            1789.18,
            "Flynn Modric is better in there, isn't he?"
        ],
        "422": [
            1789.18,
            1791.18,
            "Great little connector, the way he just keeps it going."
        ],
        "423": [
            1792.18,
            1793.18,
            "Restored some order, hasn't he?"
        ],
        "424": [
            1793.18,
            1794.18,
            "He has, yeah."
        ],
        "425": [
            1794.18,
            1797.18,
            "Kadiru couldn't really do that, wasn't able to do that alongside Kroos."
        ],
        "426": [
            1797.18,
            1798.18,
            "Didn't ever look comfortable."
        ],
        "427": [
            1799.18,
            1801.18,
            "Benzema cut that challenge from Nastasic."
        ],
        "428": [
            1816.18,
            1819.18,
            "Nastasic's challenge was on Ronaldo, I think it was on."
        ],
        "429": [
            1819.18,
            1820.18,
            "He just runs into magic there."
        ],
        "430": [
            1828.18,
            1831.18,
            "♫ We are the champions of Europe"
        ],
        "431": [
            1831.18,
            1833.18,
            "♫ And we come from London to the Poles"
        ],
        "432": [
            1833.18,
            1836.18,
            "♫ We are the champions of Europe"
        ],
        "433": [
            1836.18,
            1839.18,
            "♫ And we come from London to the Poles. ♫"
        ],
        "434": [
            1857.18,
            1858.18,
            "Maia."
        ],
        "435": [
            1859.18,
            1860.18,
            "He's been available all night long."
        ],
        "436": [
            1861.18,
            1862.18,
            "Held some really good positions."
        ],
        "437": [
            1864.18,
            1865.18,
            "Neustadt."
        ],
        "438": [
            1867.18,
            1868.18,
            "Buntelan."
        ],
        "439": [
            1869.18,
            1870.18,
            "Now Barnetta."
        ],
        "440": [
            1871.18,
            1872.18,
            "Four blue shirts in there."
        ],
        "441": [
            1872.18,
            1873.18,
            "One of them Maia."
        ],
        "442": [
            1874.18,
            1875.18,
            "Modric got back."
        ],
        "443": [
            1884.18,
            1885.18,
            "Barnetta."
        ],
        "444": [
            1885.18,
            1886.18,
            "Neustadt."
        ],
        "445": [
            1887.18,
            1888.18,
            "Sané."
        ],
        "446": [
            1888.18,
            1889.18,
            "Now Maia."
        ],
        "447": [
            1889.18,
            1890.18,
            "Now Sané."
        ],
        "448": [
            1895.18,
            1897.18,
            "Beretsky with the attempt on goal."
        ],
        "449": [
            1897.18,
            1898.18,
            "A bit intentative."
        ],
        "450": [
            1899.18,
            1900.18,
            "Good play there actually."
        ],
        "451": [
            1900.18,
            1903.18,
            "I just think Sané perhaps could have gone on his right foot."
        ],
        "452": [
            1903.18,
            1905.18,
            "Chopped back onto his left side and just..."
        ],
        "453": [
            1906.18,
            1908.18,
            "Unfortunately the move lost its momentum but..."
        ],
        "454": [
            1909.18,
            1910.18,
            "Good play once more."
        ],
        "455": [
            1911.18,
            1912.18,
            "Again with Maia just in the hole."
        ],
        "456": [
            1913.18,
            1914.18,
            "Everything going through him."
        ],
        "457": [
            1917.18,
            1918.18,
            "Rites!"
        ],
        "458": [
            1939.18,
            1940.18,
            "Go, go, and win!"
        ],
        "459": [
            1970.18,
            1972.18,
            "Modric is offside, Benzema."
        ],
        "460": [
            1977.78,
            1981.38,
            "Here's the bright news of the evening, really, for Real Madrid."
        ],
        "461": [
            1986.38,
            1988.38,
            "He's returned as if he's never been away."
        ],
        "462": [
            1990.78,
            1992.98,
            "That was Goretzka's chance, wasn't it, moments ago."
        ],
        "463": [
            1994.38,
            1997.58,
            "Offside for that one, pretty tame at Casillas."
        ],
        "464": [
            1998.58,
            2001.78,
            "Performance will have done little, I think, to please those that..."
        ],
        "465": [
            2003.38,
            2004.58,
            "...still doubt Madrid."
        ],
        "466": [
            2005.78,
            2007.38,
            "It's been hard work."
        ],
        "467": [
            2008.18,
            2010.18,
            "It's been very little to really cheer about."
        ],
        "468": [
            2010.18,
            2011.58,
            "I think we give them credit for..."
        ],
        "469": [
            2013.38,
            2017.98,
            "...the way they managed to peg the initial lead back, but it's not been a good performance from them."
        ],
        "470": [
            2019.18,
            2020.78,
            "Pappaiolli as far as Fuchs."
        ],
        "471": [
            2022.78,
            2024.58,
            "Casillas feels that..."
        ],
        "472": [
            2025.58,
            2026.58,
            "...favorably enough."
        ],
        "473": [
            2028.58,
            2032.58,
            "They're going to have to find some gears between now and when is it?"
        ],
        "474": [
            2032.58,
            2033.58,
            "Classico? 12 days?"
        ],
        "475": [
            2033.58,
            2034.58,
            "Saturday week."
        ],
        "476": [
            2037.58,
            2040.58,
            "They have to find an edge to their game. It's all been a little bit..."
        ],
        "477": [
            2040.58,
            2043.58,
            "...one-paced. Roy mentioned at half-time about the fact that..."
        ],
        "478": [
            2043.58,
            2045.58,
            "...in Colz they had that lead yet."
        ],
        "479": [
            2045.58,
            2046.58,
            "I think that's true."
        ],
        "480": [
            2046.58,
            2049.58,
            "I think because they already came here tonight with two goals in their back pocket..."
        ],
        "481": [
            2049.58,
            2054.58,
            "...does perhaps take the sting out of the game initially, but..."
        ],
        "482": [
            2055.58,
            2058.58,
            "...I just think they were slow in their first 20 minutes, predictable..."
        ],
        "483": [
            2058.58,
            2060.58,
            "...and wide open as well, and easily got out."
        ],
        "484": [
            2065.58,
            2068.58,
            "Ronaldo inviting Arboloa to come forward."
        ],
        "485": [
            2070.58,
            2072.58,
            "Frustrated that the cross didn't come in earlier."
        ],
        "486": [
            2075.58,
            2078.58,
            "It's a good ball from Kroos, not good control from Isco."
        ],
        "487": [
            2085.58,
            2088.58,
            "Ronaldo's changed for Schalke on this right-hand side."
        ],
        "488": [
            2089.58,
            2092.58,
            "Varlanete will give way to Atsuto Uchida."
        ],
        "489": [
            2098.58,
            2101.58,
            "Ronaldo's changed for Schalke on this right-hand side."
        ],
        "490": [
            2102.58,
            2105.58,
            "Varlanete will give way to Atsuto Uchida."
        ],
        "491": [
            2115.58,
            2119.58,
            "Japanese World Cup right-back is familiar with the wing-back role."
        ],
        "492": [
            2137.58,
            2138.58,
            "Goretzka."
        ],
        "493": [
            2139.58,
            2143.58,
            "It's an interesting ball too towards Montelar, slightly overhead."
        ],
        "494": [
            2145.58,
            2147.58,
            "Not quite keeping in either."
        ],
        "495": [
            2150.58,
            2152.58,
            "Lucky just a fraction too big for him, wasn't it?"
        ],
        "496": [
            2152.58,
            2154.58,
            "That ball from Goretzka was the right idea."
        ],
        "497": [
            2163.58,
            2165.58,
            "It's the tail of the tape."
        ],
        "498": [
            2168.58,
            2171.58,
            "Nothing much to choose between the two teams."
        ],
        "499": [
            2174.58,
            2177.58,
            "Goretzka did just catch Modric."
        ],
        "500": [
            2181.58,
            2184.58,
            "Actually made it into the preliminary..."
        ],
        "501": [
            2184.58,
            2187.58,
            "...they said that, World Cup squad, Goretzka."
        ],
        "502": [
            2189.58,
            2192.58,
            "He turned 20 last month. He is another young German player."
        ],
        "503": [
            2195.58,
            2198.58,
            "From Bogie Lovers High Hopes."
        ],
        "504": [
            2199.58,
            2200.58,
            "Uchida."
        ],
        "505": [
            2220.58,
            2222.58,
            "Change of right-back for Real Madrid."
        ],
        "506": [
            2222.58,
            2223.58,
            "Ronaldo."
        ],
        "507": [
            2224.58,
            2225.58,
            "Giving way to..."
        ],
        "508": [
            2226.58,
            2231.58,
            "Giving way to a pretty rare appearance from Nacho Fernandez."
        ],
        "509": [
            2235.58,
            2238.58,
            "He has been on the fringe this season."
        ],
        "510": [
            2242.58,
            2243.58,
            "First win of the ball."
        ],
        "511": [
            2247.58,
            2248.58,
            "Bale."
        ],
        "512": [
            2249.58,
            2250.58,
            "He's running back."
        ],
        "513": [
            2251.58,
            2252.58,
            "Here's Benzema."
        ],
        "514": [
            2255.58,
            2256.58,
            "Isco."
        ],
        "515": [
            2258.58,
            2259.58,
            "It's well curled."
        ],
        "516": [
            2260.58,
            2263.58,
            "Didn't quite get enough action on it. Good effort."
        ],
        "517": [
            2263.58,
            2264.58,
            "Good skill."
        ],
        "518": [
            2265.58,
            2267.58,
            "Bad idea from Isco."
        ],
        "519": [
            2268.58,
            2269.58,
            "Benzema does well."
        ],
        "520": [
            2269.58,
            2272.58,
            "Everyone's getting back in the box thinking he might want to..."
        ],
        "521": [
            2272.58,
            2273.58,
            "...hit the byline and cross it."
        ],
        "522": [
            2273.58,
            2275.58,
            "Instead he dips back onto his right foot."
        ],
        "523": [
            2275.58,
            2276.58,
            "He's got the ability to do that."
        ],
        "524": [
            2276.58,
            2278.58,
            "That's exactly what he's trying to do."
        ],
        "525": [
            2279.58,
            2281.58,
            "Goalkeeper's always struggling but..."
        ],
        "526": [
            2282.58,
            2283.58,
            "...just wide."
        ],
        "527": [
            2284.58,
            2287.58,
            "Porto will be in the quarter-final draw in 10 days time."
        ],
        "528": [
            2287.58,
            2289.58,
            "They now lead by 4 goals to nil."
        ],
        "529": [
            2289.58,
            2292.58,
            "And by 5 goals to 1 in aggregate."
        ],
        "530": [
            2292.58,
            2295.58,
            "Against Basel. Highlights of that."
        ],
        "531": [
            2295.58,
            2298.58,
            "And indeed this game on ITV at 10.40 this evening."
        ],
        "532": [
            2298.58,
            2301.58,
            "And we've got more live European football this evening."
        ],
        "533": [
            2301.58,
            2305.58,
            "Here on ITV. Everton play in the last 16 of the Europe League."
        ],
        "534": [
            2305.58,
            2307.58,
            "Against Dynamo Kiev."
        ],
        "535": [
            2307.58,
            2310.58,
            "Good signal at 7.45 on ITV."
        ],
        "536": [
            2310.58,
            2313.58,
            "If you want to see the Wolfsburg-Inter Milan game at the same stage..."
        ],
        "537": [
            2313.58,
            2315.58,
            "...that's on ITV4 a little earlier."
        ],
        "538": [
            2331.58,
            2334.58,
            "Modric made a challenge but it might come for Untular."
        ],
        "539": [
            2334.58,
            2336.58,
            "Oh! It's in!"
        ],
        "540": [
            2336.58,
            2337.58,
            "He's got another."
        ],
        "541": [
            2338.58,
            2340.58,
            "And Sarkar have got another lead."
        ],
        "542": [
            2341.58,
            2343.58,
            "And they're one away..."
        ],
        "543": [
            2344.58,
            2346.58,
            "...from winning this tie, would you believe."
        ],
        "544": [
            2347.58,
            2349.58,
            "Klaas-Jan Untular..."
        ],
        "545": [
            2349.58,
            2351.58,
            "...smashes it in off the crossbar."
        ],
        "546": [
            2351.58,
            2354.58,
            "An inadvertent pass from Luka Modric."
        ],
        "547": [
            2354.58,
            2355.58,
            "Now..."
        ],
        "548": [
            2355.58,
            2357.58,
            "Great finish."
        ],
        "549": [
            2357.58,
            2359.58,
            "You know if he takes that yard further..."
        ],
        "550": [
            2359.58,
            2361.58,
            "...he'll catch it because he's so quick across the ground."
        ],
        "551": [
            2361.58,
            2362.58,
            "But..."
        ],
        "552": [
            2362.58,
            2364.58,
            "Yeah, there's a bit of good fortune here."
        ],
        "553": [
            2364.58,
            2365.58,
            "The pass from Sané, look, just..."
        ],
        "554": [
            2365.58,
            2368.58,
            "Luka Modric just gets a toe on it, puts Untular in."
        ],
        "555": [
            2368.58,
            2370.58,
            "Hey, but what a strike."
        ],
        "556": [
            2370.58,
            2371.58,
            "Brilliant effort."
        ],
        "557": [
            2371.58,
            2373.58,
            "We criticise Casillas for some of the others, not that one."
        ],
        "558": [
            2373.58,
            2375.58,
            "Not getting anywhere near that."
        ],
        "559": [
            2376.58,
            2379.58,
            "Real Madrid's aggregate lead is 5-4."
        ],
        "560": [
            2380.58,
            2383.58,
            "But if Schalke were to find one more unanswered goal..."
        ],
        "561": [
            2383.58,
            2386.58,
            "...they would knock Real Madrid out of this competition..."
        ],
        "562": [
            2386.58,
            2388.58,
            "...on away goals."
        ],
        "563": [
            2388.58,
            2390.58,
            "Real Madrid unbeaten..."
        ],
        "564": [
            2390.58,
            2392.58,
            "...in the Champions League at the Bernabeu..."
        ],
        "565": [
            2392.58,
            2394.58,
            "...since 2011."
        ],
        "566": [
            2397.58,
            2400.58,
            "Klaas-Jan Untular, one of the old boys..."
        ],
        "567": [
            2400.58,
            2403.58,
            "...has scored two of the four Schalke goals."
        ],
        "568": [
            2406.58,
            2407.58,
            "Just now need to..."
        ],
        "569": [
            2407.58,
            2410.58,
            "...get it wide and get it in that box."
        ],
        "570": [
            2412.58,
            2414.58,
            "Take a chance."
        ],
        "571": [
            2414.58,
            2415.58,
            "Gamble with your midfield runs."
        ],
        "572": [
            2415.58,
            2416.58,
            "Just get in there."
        ],
        "573": [
            2416.58,
            2418.58,
            "Just trust someone to put it in the box..."
        ],
        "574": [
            2418.58,
            2420.58,
            "...with a little bit of pace on it."
        ],
        "575": [
            2420.58,
            2422.58,
            "Something just might drop for you."
        ],
        "576": [
            2422.58,
            2424.58,
            "The edge is anywhere."
        ],
        "577": [
            2425.58,
            2427.58,
            "I think Schalke have just acquired some new fans..."
        ],
        "578": [
            2427.58,
            2430.58,
            "...in Barcelona and Munich and West London..."
        ],
        "579": [
            2430.58,
            2432.58,
            "...and one or two other places."
        ],
        "580": [
            2432.58,
            2435.58,
            "Because it would be a sensational result."
        ],
        "581": [
            2435.58,
            2437.58,
            "Put it in the box."
        ],
        "582": [
            2437.58,
            2438.58,
            "Christian Fuchs there, he's looking for a little..."
        ],
        "583": [
            2438.58,
            2440.58,
            "...clever ball to the byline."
        ],
        "584": [
            2440.58,
            2442.58,
            "Put it in there."
        ],
        "585": [
            2443.58,
            2445.58,
            "This is the goal again, he hits it ever so well."
        ],
        "586": [
            2446.58,
            2448.58,
            "Great finish."
        ],
        "587": [
            2453.58,
            2455.58,
            "He's the oldest player in this team now."
        ],
        "588": [
            2457.58,
            2460.58,
            "So much experience, he only has 70 caps for Holland."
        ],
        "589": [
            2461.58,
            2463.58,
            "His career stalled here and in Milan..."
        ],
        "590": [
            2463.58,
            2464.58,
            "...but he's found himself in Germany..."
        ],
        "591": [
            2464.58,
            2467.58,
            "...and found lots and lots of goals."
        ],
        "592": [
            2472.58,
            2474.58,
            "Goretzka, good feed."
        ],
        "593": [
            2475.58,
            2476.58,
            "Sané."
        ],
        "594": [
            2477.58,
            2478.58,
            "Blocked by Modric."
        ],
        "595": [
            2481.58,
            2482.58,
            "Hermannes."
        ],
        "596": [
            2484.58,
            2485.58,
            "That's clever from Maier."
        ],
        "597": [
            2485.58,
            2487.58,
            "Here's Sané, away from Modric."
        ],
        "598": [
            2487.58,
            2490.58,
            "Sané's shot and Casillas had to save it."
        ],
        "599": [
            2491.58,
            2492.58,
            "Poured away for a throw in."
        ],
        "600": [
            2494.58,
            2495.58,
            "Good play."
        ],
        "601": [
            2495.58,
            2497.58,
            "Good effort there from Sané that time."
        ],
        "602": [
            2497.58,
            2500.58,
            "Casillas has enough about him to deal with it."
        ],
        "603": [
            2500.58,
            2502.58,
            "Scoops it away from his goal."
        ],
        "604": [
            2504.58,
            2507.58,
            "No team has ever lost a Champions League home leg..."
        ],
        "605": [
            2507.58,
            2510.58,
            "...by two clear goals and survived in the second leg."
        ],
        "606": [
            2511.58,
            2514.58,
            "Punch by Casillas, volley from Maier."
        ],
        "607": [
            2524.58,
            2525.58,
            "Good keep there."
        ],
        "608": [
            2527.58,
            2530.58,
            "This was the shot from Sané again."
        ],
        "609": [
            2531.58,
            2533.58,
            "This has stopped that time."
        ],
        "610": [
            2536.58,
            2539.58,
            "Busu, making sure he gets it well away from the goal..."
        ],
        "611": [
            2539.58,
            2541.58,
            "...into any onrushing blue shirts."
        ],
        "612": [
            2552.58,
            2555.58,
            "Maier, go towards Ronaldo, cut out by Messi."
        ],
        "613": [
            2555.58,
            2558.58,
            "I've got a few pals who like a flutter on the correct score."
        ],
        "614": [
            2559.58,
            2562.58,
            "Anybody out there have Real Madrid 3, Schalke 4 tonight?"
        ],
        "615": [
            2564.58,
            2565.58,
            "It's not over yet."
        ],
        "616": [
            2569.58,
            2571.58,
            "Maier, into the path of Sané."
        ],
        "617": [
            2574.58,
            2576.58,
            "Casillas is coming, eventually."
        ],
        "618": [
            2579.58,
            2582.58,
            "Sané again, trying to come back onto his left foot."
        ],
        "619": [
            2582.58,
            2585.58,
            "Sometimes you've got to go with the other foot, take a chance."
        ],
        "620": [
            2586.58,
            2588.58,
            "He let that run across his body."
        ],
        "621": [
            2588.58,
            2590.58,
            "He would have had a shot on Casillas."
        ],
        "622": [
            2592.58,
            2595.58,
            "Veto Di Matteo's run to the final with Chelsea three years ago..."
        ],
        "623": [
            2595.58,
            2597.58,
            "...was all about brinksmanship."
        ],
        "624": [
            2599.58,
            2601.58,
            "Likely wins, some unlikely positions."
        ],
        "625": [
            2601.58,
            2603.58,
            "This would cap the lot."
        ],
        "626": [
            2604.58,
            2605.58,
            "He knows it."
        ],
        "627": [
            2613.58,
            2617.58,
            "These are a critical few minutes for Real Madrid's season."
        ],
        "628": [
            2627.58,
            2628.58,
            "Goalkeeper."
        ],
        "629": [
            2628.58,
            2631.58,
            "It's the worst person you want to let have the ball there at that moment."
        ],
        "630": [
            2631.58,
            2634.58,
            "The goalkeeper, if he can transfer it pretty quickly..."
        ],
        "631": [
            2634.58,
            2636.58,
            "...he's decided to put it down and play."
        ],
        "632": [
            2636.58,
            2638.58,
            "He might regret that."
        ],
        "633": [
            2639.58,
            2642.58,
            "Full marks to them all for making the trip from Germany."
        ],
        "634": [
            2642.58,
            2645.58,
            "What seemed like a pretty hopeless mission."
        ],
        "635": [
            2645.58,
            2647.58,
            "It's not hopeless at the moment."
        ],
        "636": [
            2647.58,
            2649.58,
            "Frontalar, Sané."
        ],
        "637": [
            2651.58,
            2653.58,
            "He's kept the ball and found Maier."
        ],
        "638": [
            2654.58,
            2656.58,
            "Oh, it's just cut out by Pepe."
        ],
        "639": [
            2656.58,
            2657.58,
            "It was bound for Garetzka."
        ],
        "640": [
            2657.58,
            2659.58,
            "Maier again."
        ],
        "641": [
            2660.58,
            2662.58,
            "Header away by Pepe once more."
        ],
        "642": [
            2663.58,
            2665.58,
            "Kept alive by Fuchs."
        ],
        "643": [
            2665.58,
            2666.58,
            "Maier's onside."
        ],
        "644": [
            2667.58,
            2669.58,
            "Last of the 90 minutes."
        ],
        "645": [
            2672.58,
            2673.58,
            "Nastasic."
        ],
        "646": [
            2674.58,
            2675.58,
            "In towards Frontalar."
        ],
        "647": [
            2675.58,
            2677.58,
            "This is Hervéz!"
        ],
        "648": [
            2678.58,
            2680.58,
            "And he forced the save."
        ],
        "649": [
            2680.58,
            2684.58,
            "Casillas, who's had some bad moments tonight, has had a couple of very good ones."
        ],
        "650": [
            2684.58,
            2686.58,
            "When Real Madrid have really needed him."
        ],
        "651": [
            2687.58,
            2690.58,
            "Great leap from Frontalar as well, knocking it back to Hervéz."
        ],
        "652": [
            2690.58,
            2692.58,
            "He's done well getting in there."
        ],
        "653": [
            2692.58,
            2696.58,
            "That's not his speciality, his forte, that he's leaning away from it."
        ],
        "654": [
            2696.58,
            2699.58,
            "He's got to hit it because of the pressure he's under from Nacho."
        ],
        "655": [
            2699.58,
            2701.58,
            "But good leap from Frontalar."
        ],
        "656": [
            2701.58,
            2706.58,
            "Maybe just one of your midfield players on that one who just might get it a little bit cleaner."
        ],
        "657": [
            2706.58,
            2709.58,
            "Hits it a bit sweeter, but he does exactly the right thing."
        ],
        "658": [
            2710.58,
            2714.58,
            "He draws it on his chest and just can't get enough power into the shot."
        ],
        "659": [
            2715.58,
            2717.58,
            "Here comes the board with the added minutes. It's three."
        ],
        "660": [
            2717.58,
            2724.58,
            "Real Madrid are three minutes away from reaching the quarterfinals for the fifth consecutive year."
        ],
        "661": [
            2725.58,
            2728.58,
            "But not in a manner that anybody would have anticipated."
        ],
        "662": [
            2729.58,
            2730.58,
            "They're not there yet."
        ],
        "663": [
            2730.58,
            2731.58,
            "Here's Ronaldo."
        ],
        "664": [
            2733.58,
            2735.58,
            "Pulled back to Modric, and he took his head off."
        ],
        "665": [
            2747.58,
            2748.58,
            "Close."
        ],
        "666": [
            2749.58,
            2752.58,
            "Listen to the applause just for Real Madrid keeping the ball."
        ],
        "667": [
            2753.58,
            2754.58,
            "Just for Modric, isn't it?"
        ],
        "668": [
            2754.58,
            2756.58,
            "Just the intelligence he shows just to keep it."
        ],
        "669": [
            2766.58,
            2768.58,
            "He's had a bit more time than he realised."
        ],
        "670": [
            2768.58,
            2771.58,
            "Matip has run it back, and here's Nastasic."
        ],
        "671": [
            2772.58,
            2773.58,
            "Going with the long ball, are they?"
        ],
        "672": [
            2773.58,
            2776.58,
            "They're going to try and play their way down the field, and they can do it."
        ],
        "673": [
            2777.58,
            2778.58,
            "Frontalar feeding off Goretzka."
        ],
        "674": [
            2780.58,
            2781.58,
            "Ushida."
        ],
        "675": [
            2783.58,
            2785.58,
            "Frontalar wasn't expecting the return ball."
        ],
        "676": [
            2787.58,
            2791.58,
            "Benzema trying to take the weight off it for Ronaldo, but Matip is going to have to go for it."
        ],
        "677": [
            2792.58,
            2793.58,
            "And he's got it."
        ],
        "678": [
            2794.58,
            2795.58,
            "And he's got it."
        ],
        "679": [
            2796.58,
            2797.58,
            "And he's got it."
        ],
        "680": [
            2798.58,
            2801.58,
            "Benzema trying to take the weight off it for Ronaldo, but Matip is there."
        ],
        "681": [
            2802.58,
            2803.58,
            "Neustadter."
        ],
        "682": [
            2804.58,
            2809.58,
            "Now it's lifted in towards Ushida, and it was Marcelo who got there to concede a corner kick."
        ],
        "683": [
            2810.58,
            2811.58,
            "This is the whole time right here."
        ],
        "684": [
            2812.58,
            2813.58,
            "This corner."
        ],
        "685": [
            2815.58,
            2820.58,
            "The Real Madrid lead is effectively only half a goal, because a Schalke goal here puts them out."
        ],
        "686": [
            2825.58,
            2826.58,
            "Fuchs takes it."
        ],
        "687": [
            2827.58,
            2828.58,
            "And Casillas takes it."
        ],
        "688": [
            2830.58,
            2832.58,
            "Just didn't get the delivery right, did he there?"
        ],
        "689": [
            2832.58,
            2834.58,
            "Christian Fuchs, it's a poor one from him."
        ],
        "690": [
            2835.58,
            2838.58,
            "Just needed to be flatter and a bit pacier than that."
        ],
        "691": [
            2838.58,
            2841.58,
            "Casillas never favourite under that sort of delivery."
        ],
        "692": [
            2850.58,
            2852.58,
            "It's been a startling night for him."
        ],
        "693": [
            2855.58,
            2856.58,
            "It's nearly over."
        ],
        "694": [
            2858.58,
            2860.58,
            "Now at last, Schalke have to go long."
        ],
        "695": [
            2861.58,
            2864.58,
            "Pepe comes and wins it, and wins a free kick from Hermedez."
        ],
        "696": [
            2865.58,
            2866.58,
            "And that's probably that."
        ],
        "697": [
            2878.58,
            2880.58,
            "Yellow card I think for descent."
        ],
        "698": [
            2881.58,
            2885.58,
            "Waved in Neustadter's direction, it's Hermedez who committed the foul, maybe it's him."
        ],
        "699": [
            2888.58,
            2890.58,
            "Still can't see what Hermedez does wrong there."
        ],
        "700": [
            2891.58,
            2894.58,
            "He's just backing away, getting ready to leap and head it."
        ],
        "701": [
            2895.58,
            2896.58,
            "Pepe comes flying through him."
        ],
        "702": [
            2896.58,
            2897.58,
            "The holders go through with a great big few."
        ],
        "703": [
            2927.58,
            2928.58,
            "Beaten on the night."
        ],
        "704": [
            2930.58,
            2935.58,
            "Real Madrid's victory in Germany three weeks ago has seen them through to the quarter-finals."
        ]
    }
}